{
        "maps/bergen-trail/path-7-1.json/entities/890/settings/text": {
                "orig": "Is it a duck or a bunny? \nThe right answer eludes us all",
                "text": "Est-ce un canard ou un lapin ?\nLa bonne réponse nous échappe à tous."
        },
        "maps/bergen-trail/path-7-1.json/entities/892/settings/event/0/message": {
                "orig": "It sure looks pretty cold around here.",
                "text": "Il a l'air de faire vraiment froid ici."
        },
        "maps/bergen-trail/path-7-1.json/entities/892/settings/event/1/message": {
                "orig": "Good thing you don't really feel all that cold as an avatar.",
                "text": "C'est une bonne chose que l'on ressente pas tout le froid en tant qu'avatar."
        },
        "maps/bergen-trail/path-7-1.json/entities/892/settings/event/2/message": {
                "orig": "I heard you can configure your sensors so you properly feel the temperature... for whatever reason you'd want to do that.",
                "text": "J'ai cru comprendre qu'on pouvait configurer nos capteurs pour vraiment ressentir la température... Si on a une raison de vouloir faire ça.",
                "note": "this side text fits barely"
        },
        "maps/bergen-trail/path-7-1.json/entities/893/settings/analyzable/text": {
                "orig": "Kid Goat",
                "text": "Enfant Bouc"
        },
        "maps/bergen-trail/path-7-2-1.json/entities/68/settings/event/0/message": {
                "orig": "Wait...",
                "text": "Attends..."
        },
        "maps/bergen-trail/path-7-2-1.json/entities/68/settings/event/1/message": {
                "orig": "Look at this bunny. It sure looks different don't you think?",
                "text": "Ce lapin... Il a l'air vraiment différent, tu trouves pas ?"
        },
        "maps/bergen-trail/path-7-2-1.json/entities/68/settings/event/2/message": {
                "orig": "Do not tell me there actually was a legendary bunny...",
                "text": "Ne me dis pas qu'il y avait vraiment un lapin légendaire..."
        },
        "maps/bergen-trail/path-7-2-1.json/entities/68/settings/event/3/message": {
                "orig": "...!",
                "text": "... !"
        },
        "maps/bergen-trail/path-7-2-1.json/entities/68/settings/event/4/message": {
                "orig": "Let us agree to never tell Jean, okay?",
                "text": "En tout cas il faut rien dire à Jean, OK ?"
        },
        "maps/bergen-trail/path-7-2-1.json/entities/68/settings/event/5/message": {
                "orig": "[nods]",
                "text": "[acquiesce]"
        },
        "maps/bergen-trail/path-7-2-1.json/entities/68/settings/event/6/message": {
                "orig": "Not like you could anyway I guess.",
                "text": "Ce n'est pas comme si tu pouvais..."
        },
        "maps/bergen-trail/path-7-2-1.json/entities/68/settings/event/7/message": {
                "orig": "...",
                "text": "..."
        },
        "maps/bergen-trail/path-7-2.json/entities/204/settings/event/18/message": {
                "orig": "Looks like you found the place where this \\c[3]legendary bunny\\c[0] is.",
                "text": "On dirait que tu as trouvé l'endroit où ce \\c[3]lapin légendaire\\c[0] se cache."
        },
        "maps/bergen-trail/path-7-2.json/entities/204/settings/event/19/message": {
                "orig": "...!",
                "text": "... !"
        },
        "maps/bergen-trail/path-7-2.json/entities/204/settings/event/20/message": {
                "orig": "Be careful!\\. Who knows how strong this enemy is.",
                "text": "Sois prudente !\\. On ne sait pas comment cet ennemi est fort."
        },
        "maps/bergen-trail/path-7-2.json/entities/204/settings/event/21/message": {
                "orig": "[nods]",
                "text": "[acquiesce]"
        },
        "maps/bergen-trail/path-7-2.json/entities/204/settings/event/22/message": {
                "orig": "So what do you want to do?",
                "text": "Donc qu'est-ce que tu veux faire ?"
        },
        "maps/bergen-trail/path-7-2.json/entities/204/settings/event/23/message": {
                "orig": "...",
                "text": "..."
        },
        "maps/bergen-trail/path-7-2.json/entities/204/settings/event/24/message": {
                "orig": "...",
                "text": "..."
        },
        "maps/bergen-trail/path-7-2.json/entities/204/settings/event/30/message": {
                "orig": "I am not sure if... \\.\\.\\.",
                "text": "Je ne suis pas sûr que... \\.\\.\\."
        },
        "maps/bergen-trail/path-7-2.json/entities/204/settings/event/69/message": {
                "orig": "Never mind...",
                "text": "J'ai rien dit..."
        },
        "maps/bergen-trail/path-7-2.json/entities/204/settings/event/70/message": {
                "orig": "...",
                "text": "..."
        },
        "maps/bergen-trail/path-7-2.json/entities/204/settings/event/71/message": {
                "orig": "Now is your chance Lea!",
                "text": "C'est le bon moment, Lea !"
        },
        "maps/bergen-trail/path-7-2.json/entities/204/settings/event/72/message": {
                "orig": "...!",
                "text": "... !"
        },
        "maps/bergen-trail/path-7-2.json/entities/212/settings/event/5/message": {
                "orig": "This...",
                "text": "C'est..."
        },
        "maps/bergen-trail/path-7-2.json/entities/212/settings/event/6/message": {
                "orig": "...was just a normal \\v[combat.name.gray-frobbit].",
                "text": "... C'était juste un \\v[combat.name.gray-frobbit] normal."
        },
        "maps/bergen-trail/path-7-2.json/entities/212/settings/event/7/message": {
                "orig": "...",
                "text": "..."
        },
        "maps/bergen-trail/path-7-2.json/entities/213/settings/event/0/message": {
                "orig": "What is up with these rock formations?",
                "text": "C'est quoi le problème avec ces formations rocheuses ?"
        },
        "maps/bergen-trail/path-7-2.json/entities/213/settings/event/1/message": {
                "orig": "It looks like it could collapse any second, yet it seems stable.",
                "text": "On dirait que ça pourrait s'écrouler à tout instant. Pourtant ça a l'air stable."
        },
        "maps/bergen-trail/path-7-2.json/entities/214/settings/event/0/message": {
                "orig": "I didn't expect to see any green spots at this altitude.",
                "text": "Je ne m'attendais pas à voir de la verdure à cette altitude."
        },
        "maps/bergen-trail/path-7-2.json/entities/214/settings/event/1/message": {
                "orig": "Suspicious.",
                "text": "Curieux."
        }
}